weak_nlp/__init__.py
weak_nlp/base/__init__.py
weak_nlp/classification/__init__.py
weak_nlp/classification/util.py
weak_nlp/extraction/__init__.py
weak_nlp/extraction/util.py
weak_nlp/shared/__init__.py
weak_nlp/shared/common_util.py
weak_nlp/shared/exceptions.py
weak_nlp-0.0.13.dist-info/LICENSE
weak_nlp-0.0.13.dist-info/METADATA
weak_nlp-0.0.13.dist-info/WHEEL
weak_nlp-0.0.13.dist-info/top_level.txt
weak_nlp-0.0.13.dist-info/RECORD
