Metadata-Version: 2.1
Name: weak-nlp
Version: 0.0.13
Summary: Intelligent information integration based on weak supervision
Home-page: https://github.com/code-kern-ai/weak-nlp
Author: Johannes Hötter
Author-email: johannes.hoetter@kern.ai
License: UNKNOWN
Keywords: kern.ai,machine learning,supervised learning,python
Platform: UNKNOWN
Classifier: Development Status :: 3 - Alpha
Classifier: Programming Language :: Python :: 3
Classifier: License :: OSI Approved :: MIT License
License-File: LICENSE
Requires-Dist: numpy
Requires-Dist: pandas
